pyticoop/__init__.py
pyticoop/cli.py
pyticoop/pyticoop.py
pyticoop/dolibarr/__init__.py
pyticoop/dolibarr/base.py
pyticoop/dolibarr/documents.py
pyticoop/dolibarr/exceptions.py
pyticoop/dolibarr/products.py
pyticoop/dolibarr/query.py
pyticoop/dolibarr/stockmovements.py
pyticoop-1.1.8.dist-info/licenses/AUTHORS.rst
pyticoop-1.1.8.dist-info/licenses/LICENSE
pyticoop-1.1.8.dist-info/METADATA
pyticoop-1.1.8.dist-info/WHEEL
pyticoop-1.1.8.dist-info/top_level.txt
pyticoop-1.1.8.dist-info/RECORD
