Metadata-Version: 2.4
Name: pyticoop
Version: 1.1.8
Summary: Composants Python réutilisables pour TiCoop.
Author-email: TiCoop <informatique@ticoop.fr>
Maintainer-email: TiCoop <informatique@ticoop.fr>
License: GNU General Public License v3
Project-URL: bugs, https://gitlab.com/ticoop/pyticoop/-/issues
Project-URL: changelog, https://gitlab.com/ticoop/pyticoop/-/blob/main/HISTORY.rst
Project-URL: homepage, https://gitlab.com/ticoop/pyticoop
License-File: LICENSE
License-File: AUTHORS.rst
Requires-Dist: typer
Provides-Extra: dev
Requires-Dist: coverage; extra == "dev"
Requires-Dist: mypy; extra == "dev"
Requires-Dist: pytest; extra == "dev"
Requires-Dist: ruff; extra == "dev"
Requires-Dist: requests-mock; extra == "dev"
Dynamic: license-file
